guava/__init__.py
guava/auto_ohm.py
guava/autodiscovery_port_manager.py
guava/base_worker.py
guava/cli.py
guava/config.py
guava/energy_monitor.py
guava/network_worker.py
guava/ohm_reader.py
guava/orchestrator.py
guava/post_install.py
guava/protocol.py
guava/socket_utils.py
guava/training_components.py
guava_ml-0.1.0.dist-info/licenses/LICENSE
guava_ml-0.1.0.dist-info/METADATA
guava_ml-0.1.0.dist-info/WHEEL
guava_ml-0.1.0.dist-info/entry_points.txt
guava_ml-0.1.0.dist-info/top_level.txt
guava_ml-0.1.0.dist-info/RECORD
